datasense/__init__.py
datasense/_version.py
datasense/analyze_data.py
datasense/feature_importance.py
datasense/missing_values.py
datasense/outliers.py
datasense/recommendations.py
datasense/stats.py
datasense/summary.py
datasense/timeseries.py
datasense/visualization.py
datasense_eda-0.1.2.dist-info/licenses/LICENSE.txt
datasense_eda-0.1.2.dist-info/METADATA
datasense_eda-0.1.2.dist-info/WHEEL
datasense_eda-0.1.2.dist-info/top_level.txt
datasense_eda-0.1.2.dist-info/RECORD
