Metadata-Version: 2.4
Name: datasense-eda
Version: 0.1.2
Summary: Datasense: An Explainable EDA library for automated exploratory data analysis, outlier detection, feature importance, and visualization.
Home-page: https://github.com/Akash-Sare03/datasense
Author: Akash Sare
Author-email: Akash Sare <akashsare03@gmail.com>
License: MIT
Project-URL: Bug Tracker, https://github.com/Akash-Sare03/datasense/issues
Project-URL: Source Code, https://github.com/Akash-Sare03/datasense
Project-URL: Documentation, https://github.com/Akash-Sare03/datasense#readme
Classifier: Development Status :: 4 - Beta
Classifier: Intended Audience :: Science/Research
Classifier: Intended Audience :: Developers
Classifier: Intended Audience :: Education
Classifier: Topic :: Scientific/Engineering :: Information Analysis
Classifier: Topic :: Scientific/Engineering :: Visualization
Classifier: Programming Language :: Python :: 3
Classifier: Programming Language :: Python :: 3.7
Classifier: Programming Language :: Python :: 3.8
Classifier: Programming Language :: Python :: 3.9
Classifier: Programming Language :: Python :: 3.10
Classifier: License :: OSI Approved :: MIT License
Classifier: Operating System :: OS Independent
Requires-Python: >=3.7
License-File: LICENSE.txt
Requires-Dist: pandas>=1.2.0
Requires-Dist: numpy>=1.19.0
Requires-Dist: scipy>=1.6.0
Requires-Dist: scikit-learn>=0.24.0
Requires-Dist: statsmodels>=0.12.0
Requires-Dist: seaborn>=0.11.0
Requires-Dist: matplotlib>=3.3.0
Requires-Dist: ipython>=7.0.0
Requires-Dist: tabulate
Dynamic: author
Dynamic: home-page
Dynamic: license-file
Dynamic: requires-python
